fuzzly_users/__init__.py
fuzzly_users/api.py
fuzzly_users/constants.py
fuzzly_users/internal.py
fuzzly_users/models.py
fuzzly_users-0.0.3.dist-info/LICENSE
fuzzly_users-0.0.3.dist-info/METADATA
fuzzly_users-0.0.3.dist-info/WHEEL
fuzzly_users-0.0.3.dist-info/top_level.txt
fuzzly_users-0.0.3.dist-info/RECORD
